{"nodes": [{"name": "Cafes", "group": 0}, {"name": "Coffee & Tea", "group": 0}, {"name": "Delis", "group": 0}, {"name": "Food Delivery Services", "group": 0}, {"name": "Italian", "group": 0}, {"name": "Pizza", "group": 0}, {"name": "Tea Rooms", "group": 0}, {"name": "Asian Fusion", "group": 1}, {"name": "Bakeries", "group": 1}, {"name": "Beer, Wine & Spirits", "group": 1}, {"name": "Buffets", "group": 1}, {"name": "Chinese", "group": 1}, {"name": "Desserts", "group": 1}, {"name": "Dim Sum", "group": 1}, {"name": "Diners", "group": 1}, {"name": "French", "group": 1}, {"name": "Japanese", "group": 1}, {"name": "Juice Bars & Smoothies", "group": 1}, {"name": "Salad", "group": 1}, {"name": "Seafood", "group": 1}, {"name": "Steakhouses", "group": 1}, {"name": "Sushi Bars", "group": 1}, {"name": "Barbeque", "group": 2}, {"name": "Burgers", "group": 2}, {"name": "Caterers", "group": 2}, {"name": "Ethnic Food", "group": 2}, {"name": "Mexican", "group": 2}, {"name": "Specialty Food", "group": 2}, {"name": "Tex-Mex", "group": 2}, {"name": "American (Traditional)", "group": 3}, {"name": "Sports Bars", "group": 3}, {"name": "American (New)", "group": 4}, {"name": "Bars", "group": 4}, {"name": "Brasseries", "group": 4}, {"name": "British", "group": 4}, {"name": "Cocktail Bars", "group": 4}, {"name": "Gastropubs", "group": 4}, {"name": "Lounges", "group": 4}, {"name": "Modern European", "group": 4}, {"name": "Pubs", "group": 4}, {"name": "Wine Bars", "group": 4}, {"name": "Halal", "group": 5}, {"name": "Mediterranean", "group": 5}, {"name": "Sandwiches", "group": 6}, {"name": "Gluten-Free", "group": 7}, {"name": "Vegan", "group": 7}, {"name": "Vegetarian", "group": 7}, {"name": "Breakfast & Brunch", "group": 8}, {"name": "Comfort Food", "group": 8}, {"name": "Fruits & Veggies", "group": 8}], "links": [{"source": 0, "target": 1, "value": 0.3137585297121656}, {"source": 0, "target": 2, "value": 0.08442317188073757}, {"source": 0, "target": 3, "value": 0.15024621229325544}, {"source": 0, "target": 4, "value": 0.07856730757724294}, {"source": 0, "target": 5, "value": 0.08988273179593458}, {"source": 0, "target": 6, "value": 0.344161560178995}, {"source": 0, "target": 7, "value": 0.07108302985334397}, {"source": 0, "target": 8, "value": 0.22140032827889553}, {"source": 0, "target": 9, "value": 0.06273182426573873}, {"source": 0, "target": 10, "value": 0.06625208684562967}, {"source": 0, "target": 11, "value": 0.07314369069387107}, {"source": 0, "target": 12, "value": 0.12632994543276968}, {"source": 0, "target": 13, "value": 0.026640709828849394}, {"source": 0, "target": 14, "value": 0.12585683133323933}, {"source": 0, "target": 15, "value": 0.04605165652687}, {"source": 0, "target": 16, "value": 0.04091290304366306}, {"source": 0, "target": 17, "value": 0.07898112324219303}, {"source": 0, "target": 18, "value": 0.10443698558912327}, {"source": 0, "target": 19, "value": 0.08534862322102844}, {"source": 0, "target": 20, "value": 0.07715992837570489}, {"source": 0, "target": 21, "value": 0.04217339284798588}, {"source": 0, "target": 22, "value": 0.0740869159022403}, {"source": 0, "target": 23, "value": 0.09856398365530857}, {"source": 0, "target": 24, "value": 0.08820590017033375}, {"source": 0, "target": 25, "value": 0.015117832653805912}, {"source": 0, "target": 26, "value": 0.08860311127099874}, {"source": 0, "target": 27, "value": 0.04131778948269348}, {"source": 0, "target": 28, "value": 0.07070216870876549}, {"source": 0, "target": 29, "value": 0.17639505034916925}, {"source": 0, "target": 30, "value": 0.06812962471156925}, {"source": 0, "target": 31, "value": 0.1741370371576813}, {"source": 0, "target": 32, "value": 0.15211701810884876}, {"source": 0, "target": 33, "value": 0.08753782889633958}, {"source": 0, "target": 34, "value": 0.054925824561341194}, {"source": 0, "target": 35, "value": 0.06937661320069426}, {"source": 0, "target": 36, "value": 0.0717701151959002}, {"source": 0, "target": 37, "value": 0.07064385621060118}, {"source": 0, "target": 38, "value": 0.06039131141241624}, {"source": 0, "target": 39, "value": 0.06922400806546748}, {"source": 0, "target": 40, "value": 0.0707604995665049}, {"source": 0, "target": 41, "value": 0.029264263113765794}, {"source": 0, "target": 42, "value": 0.07385547649779112}, {"source": 0, "target": 43, "value": 0.18876049883970095}, {"source": 0, "target": 44, "value": 0.09932424855300556}, {"source": 0, "target": 45, "value": 0.10955357856963076}, {"source": 0, "target": 46, "value": 0.09143359345059186}, {"source": 0, "target": 47, "value": 0.2065296113502701}, {"source": 0, "target": 48, "value": 0.07746406131336313}, {"source": 0, "target": 49, "value": 0.2726093849026451}, {"source": 1, "target": 2, "value": 0.0738973595047241}, {"source": 1, "target": 3, "value": 0.10803055491211928}, {"source": 1, "target": 4, "value": 0.07020213366506188}, {"source": 1, "target": 5, "value": 0.08227813297522947}, {"source": 1, "target": 6, "value": 0.5123304043963147}, {"source": 1, "target": 7, "value": 0.06214233808202717}, {"source": 1, "target": 8, "value": 0.2154216362688615}, {"source": 1, "target": 9, "value": 0.054970684682329636}, {"source": 1, "target": 10, "value": 0.04982656047731564}, {"source": 1, "target": 11, "value": 0.062466136046395115}, {"source": 1, "target": 12, "value": 0.12763919615544708}, {"source": 1, "target": 13, "value": 0.023369316849138955}, {"source": 1, "target": 14, "value": 0.08514649019081497}, {"source": 1, "target": 15, "value": 0.03830825277497893}, {"source": 1, "target": 16, "value": 0.03610914590525013}, {"source": 1, "target": 17, "value": 0.09986697335430672}, {"source": 1, "target": 18, "value": 0.08235217448357159}, {"source": 1, "target": 19, "value": 0.06827072280147782}, {"source": 1, "target": 20, "value": 0.05875272756443465}, {"source": 1, "target": 21, "value": 0.03688175028935512}, {"source": 1, "target": 22, "value": 0.06336350763787373}, {"source": 1, "target": 23, "value": 0.07885926231770442}, {"source": 1, "target": 24, "value": 0.06618495977992245}, {"source": 1, "target": 25, "value": 0.011753643180039389}, {"source": 1, "target": 26, "value": 0.04737587819496197}, {"source": 1, "target": 27, "value": 0.031375090753271995}, {"source": 1, "target": 28, "value": 0.054059493146409995}, {"source": 1, "target": 29, "value": 0.12251622106819442}, {"source": 1, "target": 30, "value": 0.057188557320091885}, {"source": 1, "target": 31, "value": 0.1248217892748948}, {"source": 1, "target": 32, "value": 0.12866609049041047}, {"source": 1, "target": 33, "value": 0.1152387408839235}, {"source": 1, "target": 34, "value": 0.0634448610946709}, {"source": 1, "target": 35, "value": 0.05917198302669455}, {"source": 1, "target": 36, "value": 0.059626322731648654}, {"source": 1, "target": 37, "value": 0.057483790241244184}, {"source": 1, "target": 38, "value": 0.09221095538131707}, {"source": 1, "target": 39, "value": 0.06540021901730105}, {"source": 1, "target": 40, "value": 0.06268856313727346}, {"source": 1, "target": 41, "value": 0.025026166817393166}, {"source": 1, "target": 42, "value": 0.06466737718047158}, {"source": 1, "target": 43, "value": 0.23976092076326916}, {"source": 1, "target": 44, "value": 0.09469666667750602}, {"source": 1, "target": 45, "value": 0.14729646879959224}, {"source": 1, "target": 46, "value": 0.0950163803078943}, {"source": 1, "target": 47, "value": 0.1975177103141537}, {"source": 1, "target": 48, "value": 0.053167432324478126}, {"source": 1, "target": 49, "value": 0.13083910008239238}, {"source": 2, "target": 3, "value": 0.7010341379199054}, {"source": 2, "target": 4, "value": 0.09106298606698125}, {"source": 2, "target": 5, "value": 0.10239644203003159}, {"source": 2, "target": 6, "value": 0.03980793506561737}, {"source": 2, "target": 7, "value": 0.052277352410955186}, {"source": 2, "target": 8, "value": 0.10474640983698592}, {"source": 2, "target": 9, "value": 0.04845314514068105}, {"source": 2, "target": 10, "value": 0.04515399053861384}, {"source": 2, "target": 11, "value": 0.05728272470082161}, {"source": 2, "target": 12, "value": 0.0725290238789593}, {"source": 2, "target": 13, "value": 0.019959188281611376}, {"source": 2, "target": 14, "value": 0.0720683892321571}, {"source": 2, "target": 15, "value": 0.024334117722331544}, {"source": 2, "target": 16, "value": 0.031271902170933015}, {"source": 2, "target": 17, "value": 0.04050520657721044}, {"source": 2, "target": 18, "value": 0.09021136826151294}, {"source": 2, "target": 19, "value": 0.05825645700552691}, {"source": 2, "target": 20, "value": 0.046575513799968764}, {"source": 2, "target": 21, "value": 0.0322617082891715}, {"source": 2, "target": 22, "value": 0.06138189443292466}, {"source": 2, "target": 23, "value": 0.07193881349815155}, {"source": 2, "target": 24, "value": 0.10967712347322818}, {"source": 2, "target": 25, "value": 0.024691326502938832}, {"source": 2, "target": 26, "value": 0.04718605009646678}, {"source": 2, "target": 27, "value": 0.03924465957208144}, {"source": 2, "target": 28, "value": 0.05162454660606303}, {"source": 2, "target": 29, "value": 0.10572737184072716}, {"source": 2, "target": 30, "value": 0.05055861940773069}, {"source": 2, "target": 31, "value": 0.09430722119505258}, {"source": 2, "target": 32, "value": 0.0979903800340741}, {"source": 2, "target": 33, "value": 0.04591120980441609}, {"source": 2, "target": 34, "value": 0.034028948744855694}, {"source": 2, "target": 35, "value": 0.03904144912613025}, {"source": 2, "target": 36, "value": 0.037668365803703564}, {"source": 2, "target": 37, "value": 0.041344807334960224}, {"source": 2, "target": 38, "value": 0.04155746021974145}, {"source": 2, "target": 39, "value": 0.04682988423361344}, {"source": 2, "target": 40, "value": 0.045268640834286354}, {"source": 2, "target": 41, "value": 0.022172426665804653}, {"source": 2, "target": 42, "value": 0.05822479134676096}, {"source": 2, "target": 43, "value": 0.3942967744332055}, {"source": 2, "target": 44, "value": 0.076961353329072}, {"source": 2, "target": 45, "value": 0.05368222249012725}, {"source": 2, "target": 46, "value": 0.06938984665890409}, {"source": 2, "target": 47, "value": 0.12928051253398898}, {"source": 2, "target": 48, "value": 0.043502538637303696}, {"source": 2, "target": 49, "value": 0.09855256479850978}, {"source": 3, "target": 4, "value": 0.19289435903413235}, {"source": 3, "target": 5, "value": 0.27239723913061903}, {"source": 3, "target": 6, "value": 0.04706716169824977}, {"source": 3, "target": 7, "value": 0.11973208750357343}, {"source": 3, "target": 8, "value": 0.12198009382764569}, {"source": 3, "target": 9, "value": 0.07951455628286401}, {"source": 3, "target": 10, "value": 0.08698254550212878}, {"source": 3, "target": 11, "value": 0.23368670283188903}, {"source": 3, "target": 12, "value": 0.10127171828219739}, {"source": 3, "target": 13, "value": 0.06393447912697038}, {"source": 3, "target": 14, "value": 0.16032875473254216}, {"source": 3, "target": 15, "value": 0.03749312681866936}, {"source": 3, "target": 16, "value": 0.0631507890778602}, {"source": 3, "target": 17, "value": 0.08158180245808498}, {"source": 3, "target": 18, "value": 0.15695510702344448}, {"source": 3, "target": 19, "value": 0.10565877649573278}, {"source": 3, "target": 20, "value": 0.07945282858026084}, {"source": 3, "target": 21, "value": 0.0639245225988796}, {"source": 3, "target": 22, "value": 0.12573816246858238}, {"source": 3, "target": 23, "value": 0.13915477708666601}, {"source": 3, "target": 24, "value": 0.15518531050848622}, {"source": 3, "target": 25, "value": 0.041341844826135545}, {"source": 3, "target": 26, "value": 0.13973157502855493}, {"source": 3, "target": 27, "value": 0.07270449749469657}, {"source": 3, "target": 28, "value": 0.10914082536660091}, {"source": 3, "target": 29, "value": 0.2127459856558351}, {"source": 3, "target": 30, "value": 0.10254814963817449}, {"source": 3, "target": 31, "value": 0.17528573834743924}, {"source": 3, "target": 32, "value": 0.17956160735478457}, {"source": 3, "target": 33, "value": 0.057835032347004454}, {"source": 3, "target": 34, "value": 0.051922856182380475}, {"source": 3, "target": 35, "value": 0.07353955298257685}, {"source": 3, "target": 36, "value": 0.06605804384764798}, {"source": 3, "target": 37, "value": 0.07162070869371953}, {"source": 3, "target": 38, "value": 0.04443548882011384}, {"source": 3, "target": 39, "value": 0.08635989720780586}, {"source": 3, "target": 40, "value": 0.07861020178847453}, {"source": 3, "target": 41, "value": 0.03657464224711948}, {"source": 3, "target": 42, "value": 0.12027985899986643}, {"source": 3, "target": 43, "value": 0.5276996476828548}, {"source": 3, "target": 44, "value": 0.15411752176817636}, {"source": 3, "target": 45, "value": 0.1044087348854973}, {"source": 3, "target": 46, "value": 0.15309874381934777}, {"source": 3, "target": 47, "value": 0.19888695991012}, {"source": 3, "target": 48, "value": 0.09596532660698145}, {"source": 3, "target": 49, "value": 0.30358098949075185}, {"source": 4, "target": 5, "value": 0.3678496899907694}, {"source": 4, "target": 6, "value": 0.04615631813507623}, {"source": 4, "target": 7, "value": 0.07587573188218148}, {"source": 4, "target": 8, "value": 0.06604960560780777}, {"source": 4, "target": 9, "value": 0.10838173702512141}, {"source": 4, "target": 10, "value": 0.06033058293003697}, {"source": 4, "target": 11, "value": 0.06740056865630928}, {"source": 4, "target": 12, "value": 0.0792882312850909}, {"source": 4, "target": 13, "value": 0.025313925261727127}, {"source": 4, "target": 14, "value": 0.07551958631474644}, {"source": 4, "target": 15, "value": 0.07600139371866102}, {"source": 4, "target": 16, "value": 0.04444726706903792}, {"source": 4, "target": 17, "value": 0.0412549155590512}, {"source": 4, "target": 18, "value": 0.1126937813258718}, {"source": 4, "target": 19, "value": 0.13305540062100843}, {"source": 4, "target": 20, "value": 0.12350733423513666}, {"source": 4, "target": 21, "value": 0.04478881212679789}, {"source": 4, "target": 22, "value": 0.07129427706657429}, {"source": 4, "target": 23, "value": 0.08250587373619282}, {"source": 4, "target": 24, "value": 0.18331414772562346}, {"source": 4, "target": 25, "value": 0.011306966195067677}, {"source": 4, "target": 26, "value": 0.05023235152123422}, {"source": 4, "target": 27, "value": 0.023889957083970886}, {"source": 4, "target": 28, "value": 0.05658305482983204}, {"source": 4, "target": 29, "value": 0.13678657440551462}, {"source": 4, "target": 30, "value": 0.06556201856753069}, {"source": 4, "target": 31, "value": 0.2021229976390973}, {"source": 4, "target": 32, "value": 0.19509604384449758}, {"source": 4, "target": 33, "value": 0.06651590272067642}, {"source": 4, "target": 34, "value": 0.049462640480671206}, {"source": 4, "target": 35, "value": 0.08731619860390837}, {"source": 4, "target": 36, "value": 0.0902249844153553}, {"source": 4, "target": 37, "value": 0.09222071737606674}, {"source": 4, "target": 38, "value": 0.09127981562436555}, {"source": 4, "target": 39, "value": 0.06273203601576306}, {"source": 4, "target": 40, "value": 0.17396123115876005}, {"source": 4, "target": 41, "value": 0.023323943358065143}, {"source": 4, "target": 42, "value": 0.10698144602292889}, {"source": 4, "target": 43, "value": 0.18191799436691541}, {"source": 4, "target": 44, "value": 0.12237859548371056}, {"source": 4, "target": 45, "value": 0.0584660184773284}, {"source": 4, "target": 46, "value": 0.0789912647079074}, {"source": 4, "target": 47, "value": 0.10509635354381879}, {"source": 4, "target": 48, "value": 0.04770422743742988}, {"source": 4, "target": 49, "value": 0.05816328028088101}, {"source": 5, "target": 6, "value": 0.039761183840808526}, {"source": 5, "target": 7, "value": 0.07688497895512614}, {"source": 5, "target": 8, "value": 0.0746713863763465}, {"source": 5, "target": 9, "value": 0.08579305634390508}, {"source": 5, "target": 10, "value": 0.06279572269016906}, {"source": 5, "target": 11, "value": 0.07834430019511557}, {"source": 5, "target": 12, "value": 0.08374735974824951}, {"source": 5, "target": 13, "value": 0.028899038261828977}, {"source": 5, "target": 14, "value": 0.09000936906349011}, {"source": 5, "target": 15, "value": 0.04049165634235584}, {"source": 5, "target": 16, "value": 0.04600057198553937}, {"source": 5, "target": 17, "value": 0.051360902704691486}, {"source": 5, "target": 18, "value": 0.15564812655765498}, {"source": 5, "target": 19, "value": 0.09228185030900275}, {"source": 5, "target": 20, "value": 0.0759519086700341}, {"source": 5, "target": 21, "value": 0.04766719206673493}, {"source": 5, "target": 22, "value": 0.08940066231007619}, {"source": 5, "target": 23, "value": 0.10677273940295583}, {"source": 5, "target": 24, "value": 0.24391913416813407}, {"source": 5, "target": 25, "value": 0.013904603968896596}, {"source": 5, "target": 26, "value": 0.0605011121919537}, {"source": 5, "target": 27, "value": 0.029377510391569425}, {"source": 5, "target": 28, "value": 0.06959609363697661}, {"source": 5, "target": 29, "value": 0.15169156870969913}, {"source": 5, "target": 30, "value": 0.09348896011165168}, {"source": 5, "target": 31, "value": 0.15671117528908793}, {"source": 5, "target": 32, "value": 0.17500923002404478}, {"source": 5, "target": 33, "value": 0.04634610283640522}, {"source": 5, "target": 34, "value": 0.052552701727883296}, {"source": 5, "target": 35, "value": 0.0725429331351353}, {"source": 5, "target": 36, "value": 0.0676365532719537}, {"source": 5, "target": 37, "value": 0.07242977983310564}, {"source": 5, "target": 38, "value": 0.04842093425832929}, {"source": 5, "target": 39, "value": 0.0839154853758733}, {"source": 5, "target": 40, "value": 0.10772540214331928}, {"source": 5, "target": 41, "value": 0.02589119400816804}, {"source": 5, "target": 42, "value": 0.08168881820317493}, {"source": 5, "target": 43, "value": 0.2620041680407631}, {"source": 5, "target": 44, "value": 0.18574943736337982}, {"source": 5, "target": 45, "value": 0.07957850619739958}, {"source": 5, "target": 46, "value": 0.09422395910733009}, {"source": 5, "target": 47, "value": 0.1092772704810766}, {"source": 5, "target": 48, "value": 0.0543797987517287}, {"source": 5, "target": 49, "value": 0.08347967337788592}, {"source": 6, "target": 7, "value": 0.08295029732884009}, {"source": 6, "target": 8, "value": 0.2631578956110836}, {"source": 6, "target": 9, "value": 0.041260227995184494}, {"source": 6, "target": 10, "value": 0.028423942930383295}, {"source": 6, "target": 11, "value": 0.03528575460781617}, {"source": 6, "target": 12, "value": 0.1518431451982154}, {"source": 6, "target": 13, "value": 0.014346908139227614}, {"source": 6, "target": 14, "value": 0.034061054319077466}, {"source": 6, "target": 15, "value": 0.040207377000575785}, {"source": 6, "target": 16, "value": 0.20174586732608377}, {"source": 6, "target": 17, "value": 0.032660323041766234}, {"source": 6, "target": 18, "value": 0.03325820513335545}, {"source": 6, "target": 19, "value": 0.05911409840735425}, {"source": 6, "target": 20, "value": 0.05594610008476996}, {"source": 6, "target": 21, "value": 0.10126243938778894}, {"source": 6, "target": 22, "value": 0.03341894642681604}, {"source": 6, "target": 23, "value": 0.035523520825275656}, {"source": 6, "target": 24, "value": 0.03596911476351786}, {"source": 6, "target": 25, "value": 0.008695595514067015}, {"source": 6, "target": 26, "value": 0.02357949524309507}, {"source": 6, "target": 27, "value": 0.021957529949398036}, {"source": 6, "target": 28, "value": 0.02657543516192854}, {"source": 6, "target": 29, "value": 0.06185933484761703}, {"source": 6, "target": 30, "value": 0.03389806000916845}, {"source": 6, "target": 31, "value": 0.08908220245816162}, {"source": 6, "target": 32, "value": 0.09620061527227874}, {"source": 6, "target": 33, "value": 0.09220222079608145}, {"source": 6, "target": 34, "value": 0.10332237214154424}, {"source": 6, "target": 35, "value": 0.05251958565659378}, {"source": 6, "target": 36, "value": 0.08638297654444393}, {"source": 6, "target": 37, "value": 0.04733204321650671}, {"source": 6, "target": 38, "value": 0.06402974523768787}, {"source": 6, "target": 39, "value": 0.06396434757806312}, {"source": 6, "target": 40, "value": 0.04737288470308701}, {"source": 6, "target": 41, "value": 0.015385546369973436}, {"source": 6, "target": 42, "value": 0.04452507267404956}, {"source": 6, "target": 43, "value": 0.17041732959922415}, {"source": 6, "target": 44, "value": 0.03870158728751934}, {"source": 6, "target": 45, "value": 0.15071585206946708}, {"source": 6, "target": 46, "value": 0.04376408665696728}, {"source": 6, "target": 47, "value": 0.08848567551294856}, {"source": 6, "target": 48, "value": 0.026077783027619827}, {"source": 6, "target": 49, "value": 0.042941373242810374}, {"source": 7, "target": 8, "value": 0.04839887627752093}, {"source": 7, "target": 9, "value": 0.0502178744364308}, {"source": 7, "target": 10, "value": 0.07746492708670324}, {"source": 7, "target": 11, "value": 0.36235175550889065}, {"source": 7, "target": 12, "value": 0.060568818285996244}, {"source": 7, "target": 13, "value": 0.39274654890607497}, {"source": 7, "target": 14, "value": 0.07701859717901131}, {"source": 7, "target": 15, "value": 0.046291571876261886}, {"source": 7, "target": 16, "value": 0.3120429172212869}, {"source": 7, "target": 17, "value": 0.042130018898280046}, {"source": 7, "target": 18, "value": 0.07090476332556171}, {"source": 7, "target": 19, "value": 0.1136431494682968}, {"source": 7, "target": 20, "value": 0.08678016359928942}, {"source": 7, "target": 21, "value": 0.2509144862368548}, {"source": 7, "target": 22, "value": 0.11766426588911484}, {"source": 7, "target": 23, "value": 0.08359769285795943}, {"source": 7, "target": 24, "value": 0.06683749212693885}, {"source": 7, "target": 25, "value": 0.02252037433703526}, {"source": 7, "target": 26, "value": 0.059496566379976454}, {"source": 7, "target": 27, "value": 0.033698174396795955}, {"source": 7, "target": 28, "value": 0.060139283361987386}, {"source": 7, "target": 29, "value": 0.12259211154255344}, {"source": 7, "target": 30, "value": 0.06631623840679822}, {"source": 7, "target": 31, "value": 0.13952646704162006}, {"source": 7, "target": 32, "value": 0.18342097319787073}, {"source": 7, "target": 33, "value": 0.04717963486446799}, {"source": 7, "target": 34, "value": 0.045459754862176724}, {"source": 7, "target": 35, "value": 0.13995349995013925}, {"source": 7, "target": 36, "value": 0.06319316015644887}, {"source": 7, "target": 37, "value": 0.0890272560315573}, {"source": 7, "target": 38, "value": 0.06101958931201316}, {"source": 7, "target": 39, "value": 0.06271681331265305}, {"source": 7, "target": 40, "value": 0.06918217553061573}, {"source": 7, "target": 41, "value": 0.03312121878840365}, {"source": 7, "target": 42, "value": 0.07254876477650128}, {"source": 7, "target": 43, "value": 0.09451163758635528}, {"source": 7, "target": 44, "value": 0.1870781281323122}, {"source": 7, "target": 45, "value": 0.059270047102329984}, {"source": 7, "target": 46, "value": 0.08554874327125059}, {"source": 7, "target": 47, "value": 0.08926048663110145}, {"source": 7, "target": 48, "value": 0.045408951691449234}, {"source": 7, "target": 49, "value": 0.05538418443862648}, {"source": 8, "target": 9, "value": 0.05234159883709388}, {"source": 8, "target": 10, "value": 0.04094306160237242}, {"source": 8, "target": 11, "value": 0.04846825696161405}, {"source": 8, "target": 12, "value": 0.11967785591315826}, {"source": 8, "target": 13, "value": 0.017177680742483655}, {"source": 8, "target": 14, "value": 0.07088401639638654}, {"source": 8, "target": 15, "value": 0.04499391800495935}, {"source": 8, "target": 16, "value": 0.02730813941456644}, {"source": 8, "target": 17, "value": 0.049291897708594413}, {"source": 8, "target": 18, "value": 0.07027789309566744}, {"source": 8, "target": 19, "value": 0.05290291343954955}, {"source": 8, "target": 20, "value": 0.04463079942327452}, {"source": 8, "target": 21, "value": 0.028215506159880836}, {"source": 8, "target": 22, "value": 0.04896057796572855}, {"source": 8, "target": 23, "value": 0.0632149301591791}, {"source": 8, "target": 24, "value": 0.09426707285392757}, {"source": 8, "target": 25, "value": 0.013594053636984437}, {"source": 8, "target": 26, "value": 0.046266591958323465}, {"source": 8, "target": 27, "value": 0.033361904264914116}, {"source": 8, "target": 28, "value": 0.04404215432245689}, {"source": 8, "target": 29, "value": 0.09854543452975549}, {"source": 8, "target": 30, "value": 0.0409542264149463}, {"source": 8, "target": 31, "value": 0.09308016209237015}, {"source": 8, "target": 32, "value": 0.08809053083254849}, {"source": 8, "target": 33, "value": 0.045639585048272764}, {"source": 8, "target": 34, "value": 0.03481033926894801}, {"source": 8, "target": 35, "value": 0.03612896085720995}, {"source": 8, "target": 36, "value": 0.034971189268634975}, {"source": 8, "target": 37, "value": 0.038251211183201426}, {"source": 8, "target": 38, "value": 0.02719001988872233}, {"source": 8, "target": 39, "value": 0.04184783004959464}, {"source": 8, "target": 40, "value": 0.042154177770317346}, {"source": 8, "target": 41, "value": 0.03408516715333546}, {"source": 8, "target": 42, "value": 0.0634891186981117}, {"source": 8, "target": 43, "value": 0.14883279589470325}, {"source": 8, "target": 44, "value": 0.07212129892012861}, {"source": 8, "target": 45, "value": 0.08471493018869411}, {"source": 8, "target": 46, "value": 0.06902655586978938}, {"source": 8, "target": 47, "value": 0.12425072924576913}, {"source": 8, "target": 48, "value": 0.04358695707026832}, {"source": 8, "target": 49, "value": 0.12389595552695858}, {"source": 9, "target": 10, "value": 0.0371447402105396}, {"source": 9, "target": 11, "value": 0.0462237256962938}, {"source": 9, "target": 12, "value": 0.04728597721576193}, {"source": 9, "target": 13, "value": 0.017347735889385988}, {"source": 9, "target": 14, "value": 0.057819222320273735}, {"source": 9, "target": 15, "value": 0.03438889997840982}, {"source": 9, "target": 16, "value": 0.0289728125559044}, {"source": 9, "target": 17, "value": 0.028166560998894523}, {"source": 9, "target": 18, "value": 0.06447772069114824}, {"source": 9, "target": 19, "value": 0.0715005840960743}, {"source": 9, "target": 20, "value": 0.06007437017729732}, {"source": 9, "target": 21, "value": 0.030165132740238968}, {"source": 9, "target": 22, "value": 0.055207116533172944}, {"source": 9, "target": 23, "value": 0.07297848847759261}, {"source": 9, "target": 24, "value": 0.10739809115879304}, {"source": 9, "target": 25, "value": 0.00998673215131965}, {"source": 9, "target": 26, "value": 0.08405683733050309}, {"source": 9, "target": 27, "value": 0.020531846689166675}, {"source": 9, "target": 28, "value": 0.05818224051587127}, {"source": 9, "target": 29, "value": 0.11864320990190777}, {"source": 9, "target": 30, "value": 0.07346228838991836}, {"source": 9, "target": 31, "value": 0.1364544687386964}, {"source": 9, "target": 32, "value": 0.13736697972269837}, {"source": 9, "target": 33, "value": 0.05415596541052406}, {"source": 9, "target": 34, "value": 0.043580115472695115}, {"source": 9, "target": 35, "value": 0.07648908374637367}, {"source": 9, "target": 36, "value": 0.06546746306156803}, {"source": 9, "target": 37, "value": 0.059907620967073756}, {"source": 9, "target": 38, "value": 0.05662616752540269}, {"source": 9, "target": 39, "value": 0.06615178141335466}, {"source": 9, "target": 40, "value": 0.06141868760437994}, {"source": 9, "target": 41, "value": 0.01611288316825061}, {"source": 9, "target": 42, "value": 0.054950297218985485}, {"source": 9, "target": 43, "value": 0.08442223363297686}, {"source": 9, "target": 44, "value": 0.06288753135297372}, {"source": 9, "target": 45, "value": 0.040247683997137636}, {"source": 9, "target": 46, "value": 0.06534402926827229}, {"source": 9, "target": 47, "value": 0.07500667054670747}, {"source": 9, "target": 48, "value": 0.03729854630604031}, {"source": 9, "target": 49, "value": 0.054110448008437825}, {"source": 10, "target": 11, "value": 0.10195183210725868}, {"source": 10, "target": 12, "value": 0.06621557170578049}, {"source": 10, "target": 13, "value": 0.03153952358502368}, {"source": 10, "target": 14, "value": 0.06869936862068976}, {"source": 10, "target": 15, "value": 0.03733723305963496}, {"source": 10, "target": 16, "value": 0.04736643081372373}, {"source": 10, "target": 17, "value": 0.03291211881760608}, {"source": 10, "target": 18, "value": 0.058963863114850704}, {"source": 10, "target": 19, "value": 0.08766722516650582}, {"source": 10, "target": 20, "value": 0.06558326153964163}, {"source": 10, "target": 21, "value": 0.05006799247715247}, {"source": 10, "target": 22, "value": 0.06596365037844071}, {"source": 10, "target": 23, "value": 0.06521382744472765}, {"source": 10, "target": 24, "value": 0.053315719548011536}, {"source": 10, "target": 25, "value": 0.011856238372738427}, {"source": 10, "target": 26, "value": 0.04572536474257384}, {"source": 10, "target": 27, "value": 0.02518770252587307}, {"source": 10, "target": 28, "value": 0.04889189941312014}, {"source": 10, "target": 29, "value": 0.10399771980224559}, {"source": 10, "target": 30, "value": 0.0473466013308316}, {"source": 10, "target": 31, "value": 0.10164911420060513}, {"source": 10, "target": 32, "value": 0.103154434775272}, {"source": 10, "target": 33, "value": 0.03373637631937304}, {"source": 10, "target": 34, "value": 0.03383565549960817}, {"source": 10, "target": 35, "value": 0.045245676627767586}, {"source": 10, "target": 36, "value": 0.0420257250302005}, {"source": 10, "target": 37, "value": 0.0489994948469074}, {"source": 10, "target": 38, "value": 0.03597977277981444}, {"source": 10, "target": 39, "value": 0.04415011490804034}, {"source": 10, "target": 40, "value": 0.04673334458945006}, {"source": 10, "target": 41, "value": 0.15236861243751637}, {"source": 10, "target": 42, "value": 0.053613031810051885}, {"source": 10, "target": 43, "value": 0.08018261926244588}, {"source": 10, "target": 44, "value": 0.08694884786744918}, {"source": 10, "target": 45, "value": 0.054486602637719005}, {"source": 10, "target": 46, "value": 0.11088377742419507}, {"source": 10, "target": 47, "value": 0.07832857220864878}, {"source": 10, "target": 48, "value": 0.03437883921786943}, {"source": 10, "target": 49, "value": 0.06202715809665966}, {"source": 11, "target": 12, "value": 0.054399343322251534}, {"source": 11, "target": 13, "value": 0.48563349589157934}, {"source": 11, "target": 14, "value": 0.09103881622834929}, {"source": 11, "target": 15, "value": 0.032101084713931714}, {"source": 11, "target": 16, "value": 0.07243863728946212}, {"source": 11, "target": 17, "value": 0.04987225513733815}, {"source": 11, "target": 18, "value": 0.07180965700843459}, {"source": 11, "target": 19, "value": 0.11708804440997297}, {"source": 11, "target": 20, "value": 0.06449592825655319}, {"source": 11, "target": 21, "value": 0.07480681237593838}, {"source": 11, "target": 22, "value": 0.09548697638050692}, {"source": 11, "target": 23, "value": 0.08290422638826729}, {"source": 11, "target": 24, "value": 0.08137044723657529}, {"source": 11, "target": 25, "value": 0.026915421570663674}, {"source": 11, "target": 26, "value": 0.061522011154627444}, {"source": 11, "target": 27, "value": 0.03570082031949627}, {"source": 11, "target": 28, "value": 0.06496169835605915}, {"source": 11, "target": 29, "value": 0.1198945514438759}, {"source": 11, "target": 30, "value": 0.06378181857836855}, {"source": 11, "target": 31, "value": 0.112754384244141}, {"source": 11, "target": 32, "value": 0.1496734746076013}, {"source": 11, "target": 33, "value": 0.03549890073680537}, {"source": 11, "target": 34, "value": 0.04077752611039818}, {"source": 11, "target": 35, "value": 0.056592665658087044}, {"source": 11, "target": 36, "value": 0.04792761414627246}, {"source": 11, "target": 37, "value": 0.05887694678039104}, {"source": 11, "target": 38, "value": 0.03933211292323146}, {"source": 11, "target": 39, "value": 0.05945685049814053}, {"source": 11, "target": 40, "value": 0.05580177165454638}, {"source": 11, "target": 41, "value": 0.033739873474413005}, {"source": 11, "target": 42, "value": 0.06390194894467846}, {"source": 11, "target": 43, "value": 0.09986535052825227}, {"source": 11, "target": 44, "value": 0.13286440503649552}, {"source": 11, "target": 45, "value": 0.05986116019752096}, {"source": 11, "target": 46, "value": 0.08472041470869984}, {"source": 11, "target": 47, "value": 0.08507553265808315}, {"source": 11, "target": 48, "value": 0.045873494834617536}, {"source": 11, "target": 49, "value": 0.0702125643621476}, {"source": 12, "target": 13, "value": 0.020449636451568255}, {"source": 12, "target": 14, "value": 0.07250555462521018}, {"source": 12, "target": 15, "value": 0.0416127928944792}, {"source": 12, "target": 16, "value": 0.033668430727568505}, {"source": 12, "target": 17, "value": 0.03957333285860557}, {"source": 12, "target": 18, "value": 0.06817749855420148}, {"source": 12, "target": 19, "value": 0.08185737791360068}, {"source": 12, "target": 20, "value": 0.07915891255735588}, {"source": 12, "target": 21, "value": 0.03460761381363346}, {"source": 12, "target": 22, "value": 0.06040383003211819}, {"source": 12, "target": 23, "value": 0.07250210267033977}, {"source": 12, "target": 24, "value": 0.060019500538665206}, {"source": 12, "target": 25, "value": 0.00932286105308865}, {"source": 12, "target": 26, "value": 0.04242457601349682}, {"source": 12, "target": 27, "value": 0.022416729490851443}, {"source": 12, "target": 28, "value": 0.04722947811615294}, {"source": 12, "target": 29, "value": 0.18848041833083126}, {"source": 12, "target": 30, "value": 0.051024420619366316}, {"source": 12, "target": 31, "value": 0.19792287672658948}, {"source": 12, "target": 32, "value": 0.11420155527083276}, {"source": 12, "target": 33, "value": 0.04861154684084442}, {"source": 12, "target": 34, "value": 0.038458273155810914}, {"source": 12, "target": 35, "value": 0.049653309482812366}, {"source": 12, "target": 36, "value": 0.05035407683469007}, {"source": 12, "target": 37, "value": 0.056532374810952774}, {"source": 12, "target": 38, "value": 0.04563098672898227}, {"source": 12, "target": 39, "value": 0.04948860605700451}, {"source": 12, "target": 40, "value": 0.05685717411505987}, {"source": 12, "target": 41, "value": 0.03164540839725283}, {"source": 12, "target": 42, "value": 0.06041593494950872}, {"source": 12, "target": 43, "value": 0.12122584750525602}, {"source": 12, "target": 44, "value": 0.07480761605695174}, {"source": 12, "target": 45, "value": 0.06684320271000598}, {"source": 12, "target": 46, "value": 0.07203627069572804}, {"source": 12, "target": 47, "value": 0.10251198002629835}, {"source": 12, "target": 48, "value": 0.041582146441526385}, {"source": 12, "target": 49, "value": 0.08596844060128343}, {"source": 13, "target": 14, "value": 0.03259129007859792}, {"source": 13, "target": 15, "value": 0.012767822550963483}, {"source": 13, "target": 16, "value": 0.025405452996809793}, {"source": 13, "target": 17, "value": 0.01727185343336984}, {"source": 13, "target": 18, "value": 0.025206559774653945}, {"source": 13, "target": 19, "value": 0.0654023572842106}, {"source": 13, "target": 20, "value": 0.02498160803180596}, {"source": 13, "target": 21, "value": 0.024571747044800023}, {"source": 13, "target": 22, "value": 0.03318636813698417}, {"source": 13, "target": 23, "value": 0.03059298592766282}, {"source": 13, "target": 24, "value": 0.02774895205228526}, {"source": 13, "target": 25, "value": 0.0069508286264690945}, {"source": 13, "target": 26, "value": 0.021465672447888235}, {"source": 13, "target": 27, "value": 0.010710903920321334}, {"source": 13, "target": 28, "value": 0.023535938072752116}, {"source": 13, "target": 29, "value": 0.0446843427688767}, {"source": 13, "target": 30, "value": 0.02422117225295754}, {"source": 13, "target": 31, "value": 0.042505108161768564}, {"source": 13, "target": 32, "value": 0.1332007876817729}, {"source": 13, "target": 33, "value": 0.014227389733569627}, {"source": 13, "target": 34, "value": 0.01650809852284445}, {"source": 13, "target": 35, "value": 0.022848652232831803}, {"source": 13, "target": 36, "value": 0.01871456180852712}, {"source": 13, "target": 37, "value": 0.0234065442504964}, {"source": 13, "target": 38, "value": 0.01723849981593489}, {"source": 13, "target": 39, "value": 0.02322724629888007}, {"source": 13, "target": 40, "value": 0.02108801879142473}, {"source": 13, "target": 41, "value": 0.012321036376845743}, {"source": 13, "target": 42, "value": 0.023516068266210145}, {"source": 13, "target": 43, "value": 0.035472350130105995}, {"source": 13, "target": 44, "value": 0.03739255633633443}, {"source": 13, "target": 45, "value": 0.02141601461363092}, {"source": 13, "target": 46, "value": 0.029894581151206804}, {"source": 13, "target": 47, "value": 0.03135375965716273}, {"source": 13, "target": 48, "value": 0.015381475973669931}, {"source": 13, "target": 49, "value": 0.01960381474679329}, {"source": 14, "target": 15, "value": 0.0369574371097515}, {"source": 14, "target": 16, "value": 0.0479020422282689}, {"source": 14, "target": 17, "value": 0.05127534877891805}, {"source": 14, "target": 18, "value": 0.10097473904174822}, {"source": 14, "target": 19, "value": 0.09663258376694957}, {"source": 14, "target": 20, "value": 0.08239919704089077}, {"source": 14, "target": 21, "value": 0.05179388403851821}, {"source": 14, "target": 22, "value": 0.09946204563162085}, {"source": 14, "target": 23, "value": 0.12086774608335106}, {"source": 14, "target": 24, "value": 0.08462788647011416}, {"source": 14, "target": 25, "value": 0.01438159535371446}, {"source": 14, "target": 26, "value": 0.0615156444432716}, {"source": 14, "target": 27, "value": 0.036259273546099244}, {"source": 14, "target": 28, "value": 0.07390738163779453}, {"source": 14, "target": 29, "value": 0.26302372990618006}, {"source": 14, "target": 30, "value": 0.0831126173512567}, {"source": 14, "target": 31, "value": 0.1587127611337453}, {"source": 14, "target": 32, "value": 0.15416269752211997}, {"source": 14, "target": 33, "value": 0.05539838723747128}, {"source": 14, "target": 34, "value": 0.045242551633291286}, {"source": 14, "target": 35, "value": 0.060547901818153504}, {"source": 14, "target": 36, "value": 0.055360032879102336}, {"source": 14, "target": 37, "value": 0.06828356043751137}, {"source": 14, "target": 38, "value": 0.04063418945594844}, {"source": 14, "target": 39, "value": 0.07366554007323013}, {"source": 14, "target": 40, "value": 0.06275113277452782}, {"source": 14, "target": 41, "value": 0.02506145247516274}, {"source": 14, "target": 42, "value": 0.08798528229700381}, {"source": 14, "target": 43, "value": 0.14097585357482847}, {"source": 14, "target": 44, "value": 0.1021998125866031}, {"source": 14, "target": 45, "value": 0.06499942990040758}, {"source": 14, "target": 46, "value": 0.09046182214775546}, {"source": 14, "target": 47, "value": 0.216217366422973}, {"source": 14, "target": 48, "value": 0.07392207766939907}, {"source": 14, "target": 49, "value": 0.257502405845763}, {"source": 15, "target": 16, "value": 0.023508546953865773}, {"source": 15, "target": 17, "value": 0.018243483099323526}, {"source": 15, "target": 18, "value": 0.0365964562913215}, {"source": 15, "target": 19, "value": 0.09620549946699639}, {"source": 15, "target": 20, "value": 0.1231914697975727}, {"source": 15, "target": 21, "value": 0.024264029517746703}, {"source": 15, "target": 22, "value": 0.029959717577894927}, {"source": 15, "target": 23, "value": 0.03586854718793304}, {"source": 15, "target": 24, "value": 0.03904261395494607}, {"source": 15, "target": 25, "value": 0.004929872095348825}, {"source": 15, "target": 26, "value": 0.02288256827572081}, {"source": 15, "target": 27, "value": 0.011675297381339787}, {"source": 15, "target": 28, "value": 0.02404203616533888}, {"source": 15, "target": 29, "value": 0.07498989951829041}, {"source": 15, "target": 30, "value": 0.02659422152361056}, {"source": 15, "target": 31, "value": 0.1809658779238467}, {"source": 15, "target": 32, "value": 0.11245673279615459}, {"source": 15, "target": 33, "value": 0.11999759342665191}, {"source": 15, "target": 34, "value": 0.041135005316849674}, {"source": 15, "target": 35, "value": 0.0594717355510501}, {"source": 15, "target": 36, "value": 0.07274926955196465}, {"source": 15, "target": 37, "value": 0.09606777730979042}, {"source": 15, "target": 38, "value": 0.14244311426758557}, {"source": 15, "target": 39, "value": 0.030100606735816472}, {"source": 15, "target": 40, "value": 0.07277775733109958}, {"source": 15, "target": 41, "value": 0.01220945270519749}, {"source": 15, "target": 42, "value": 0.07869546107817942}, {"source": 15, "target": 43, "value": 0.04846656721738896}, {"source": 15, "target": 44, "value": 0.03877106726845201}, {"source": 15, "target": 45, "value": 0.02544140662627297}, {"source": 15, "target": 46, "value": 0.037704958346352145}, {"source": 15, "target": 47, "value": 0.08973076106187958}, {"source": 15, "target": 48, "value": 0.026423468180948574}, {"source": 15, "target": 49, "value": 0.03036597304004804}, {"source": 16, "target": 17, "value": 0.02334802154693399}, {"source": 16, "target": 18, "value": 0.039884942667390226}, {"source": 16, "target": 19, "value": 0.08714610797281507}, {"source": 16, "target": 20, "value": 0.06650452018248164}, {"source": 16, "target": 21, "value": 0.7689558719775859}, {"source": 16, "target": 22, "value": 0.05067095928617763}, {"source": 16, "target": 23, "value": 0.04776261335978384}, {"source": 16, "target": 24, "value": 0.03856047385722978}, {"source": 16, "target": 25, "value": 0.016275304879953253}, {"source": 16, "target": 26, "value": 0.03260017047906292}, {"source": 16, "target": 27, "value": 0.021372900662557738}, {"source": 16, "target": 28, "value": 0.03643849291002756}, {"source": 16, "target": 29, "value": 0.07294638796068137}, {"source": 16, "target": 30, "value": 0.04017281935205379}, {"source": 16, "target": 31, "value": 0.07350415225153897}, {"source": 16, "target": 32, "value": 0.08678548244943503}, {"source": 16, "target": 33, "value": 0.02366301719705193}, {"source": 16, "target": 34, "value": 0.026490412079546558}, {"source": 16, "target": 35, "value": 0.0937942365242726}, {"source": 16, "target": 36, "value": 0.032125374886813135}, {"source": 16, "target": 37, "value": 0.047017126711267}, {"source": 16, "target": 38, "value": 0.043386990812824}, {"source": 16, "target": 39, "value": 0.0372665592638993}, {"source": 16, "target": 40, "value": 0.037298178131062544}, {"source": 16, "target": 41, "value": 0.016599633348305668}, {"source": 16, "target": 42, "value": 0.03929665167782363}, {"source": 16, "target": 43, "value": 0.05618651317672318}, {"source": 16, "target": 44, "value": 0.06397626221791887}, {"source": 16, "target": 45, "value": 0.03342821010471369}, {"source": 16, "target": 46, "value": 0.04645313111711922}, {"source": 16, "target": 47, "value": 0.05130636224089367}, {"source": 16, "target": 48, "value": 0.025640531791629093}, {"source": 16, "target": 49, "value": 0.03319877326404274}, {"source": 17, "target": 18, "value": 0.09486857581252266}, {"source": 17, "target": 19, "value": 0.04184866159282814}, {"source": 17, "target": 20, "value": 0.03420274435685663}, {"source": 17, "target": 21, "value": 0.024167680379438658}, {"source": 17, "target": 22, "value": 0.044341216511960484}, {"source": 17, "target": 23, "value": 0.05449505852105576}, {"source": 17, "target": 24, "value": 0.049924960511490125}, {"source": 17, "target": 25, "value": 0.010337058614196969}, {"source": 17, "target": 26, "value": 0.033160839134498105}, {"source": 17, "target": 27, "value": 0.02040830480433422}, {"source": 17, "target": 28, "value": 0.036004037183475376}, {"source": 17, "target": 29, "value": 0.07611142225379981}, {"source": 17, "target": 30, "value": 0.03389042431267553}, {"source": 17, "target": 31, "value": 0.09746563562096208}, {"source": 17, "target": 32, "value": 0.07097717011982639}, {"source": 17, "target": 33, "value": 0.026000323169633625}, {"source": 17, "target": 34, "value": 0.024089722128736092}, {"source": 17, "target": 35, "value": 0.028367373290216165}, {"source": 17, "target": 36, "value": 0.028072954090573032}, {"source": 17, "target": 37, "value": 0.03152475459802192}, {"source": 17, "target": 38, "value": 0.022830817983228786}, {"source": 17, "target": 39, "value": 0.03442044539164197}, {"source": 17, "target": 40, "value": 0.03357925123826435}, {"source": 17, "target": 41, "value": 0.013568210082880653}, {"source": 17, "target": 42, "value": 0.04081360840463413}, {"source": 17, "target": 43, "value": 0.09732051301135351}, {"source": 17, "target": 44, "value": 0.0868206732158167}, {"source": 17, "target": 45, "value": 0.25010496616845623}, {"source": 17, "target": 46, "value": 0.17259731309564524}, {"source": 17, "target": 47, "value": 0.07719877474433744}, {"source": 17, "target": 48, "value": 0.030577538090253823}, {"source": 17, "target": 49, "value": 0.06246801561548382}, {"source": 18, "target": 19, "value": 0.07946531095205805}, {"source": 18, "target": 20, "value": 0.06948872100512848}, {"source": 18, "target": 21, "value": 0.04122842822798209}, {"source": 18, "target": 22, "value": 0.08377490474147863}, {"source": 18, "target": 23, "value": 0.10903834939787348}, {"source": 18, "target": 24, "value": 0.23608063713984703}, {"source": 18, "target": 25, "value": 0.014601483842899159}, {"source": 18, "target": 26, "value": 0.06120747329492437}, {"source": 18, "target": 27, "value": 0.03386263737683433}, {"source": 18, "target": 28, "value": 0.06550306936276407}, {"source": 18, "target": 29, "value": 0.15591492522007355}, {"source": 18, "target": 30, "value": 0.06528012822667423}, {"source": 18, "target": 31, "value": 0.19196569558502327}, {"source": 18, "target": 32, "value": 0.1573192919949466}, {"source": 18, "target": 33, "value": 0.05946645857552486}, {"source": 18, "target": 34, "value": 0.0423791678201992}, {"source": 18, "target": 35, "value": 0.10539069398718025}, {"source": 18, "target": 36, "value": 0.13685173810557213}, {"source": 18, "target": 37, "value": 0.07506697140865462}, {"source": 18, "target": 38, "value": 0.04457400251447859}, {"source": 18, "target": 39, "value": 0.06925412349382588}, {"source": 18, "target": 40, "value": 0.08271755828000779}, {"source": 18, "target": 41, "value": 0.024698675754665812}, {"source": 18, "target": 42, "value": 0.08332430307241115}, {"source": 18, "target": 43, "value": 0.26716835597197364}, {"source": 18, "target": 44, "value": 0.11851740914913192}, {"source": 18, "target": 45, "value": 0.07696897543537426}, {"source": 18, "target": 46, "value": 0.17564517549885295}, {"source": 18, "target": 47, "value": 0.14993854180525099}, {"source": 18, "target": 48, "value": 0.0704921088658213}, {"source": 18, "target": 49, "value": 0.17378233790858605}, {"source": 19, "target": 20, "value": 0.3213910515922138}, {"source": 19, "target": 21, "value": 0.1087769650732113}, {"source": 19, "target": 22, "value": 0.08722833970708195}, {"source": 19, "target": 23, "value": 0.09372696374859399}, {"source": 19, "target": 24, "value": 0.08367558258665049}, {"source": 19, "target": 25, "value": 0.013882643300765576}, {"source": 19, "target": 26, "value": 0.08126993810393568}, {"source": 19, "target": 27, "value": 0.029458875056573693}, {"source": 19, "target": 28, "value": 0.07165054287608132}, {"source": 19, "target": 29, "value": 0.2272137906863427}, {"source": 19, "target": 30, "value": 0.07894413775539752}, {"source": 19, "target": 31, "value": 0.2775507931138764}, {"source": 19, "target": 32, "value": 0.20526104944992254}, {"source": 19, "target": 33, "value": 0.0793706639985735}, {"source": 19, "target": 34, "value": 0.059561309079388655}, {"source": 19, "target": 35, "value": 0.09671814031894735}, {"source": 19, "target": 36, "value": 0.09711753981483243}, {"source": 19, "target": 37, "value": 0.11645855392923453}, {"source": 19, "target": 38, "value": 0.11552811539803631}, {"source": 19, "target": 39, "value": 0.0771063338812496}, {"source": 19, "target": 40, "value": 0.10792446819684048}, {"source": 19, "target": 41, "value": 0.02711867146566858}, {"source": 19, "target": 42, "value": 0.10828348932836776}, {"source": 19, "target": 43, "value": 0.10807399645605026}, {"source": 19, "target": 44, "value": 0.11182193800732562}, {"source": 19, "target": 45, "value": 0.054321303432877686}, {"source": 19, "target": 46, "value": 0.08333307205818159}, {"source": 19, "target": 47, "value": 0.12244964501130796}, {"source": 19, "target": 48, "value": 0.06239036782328324}, {"source": 19, "target": 49, "value": 0.056361566130024014}, {"source": 20, "target": 21, "value": 0.08173294516833692}, {"source": 20, "target": 22, "value": 0.07751411412535564}, {"source": 20, "target": 23, "value": 0.07923543331168843}, {"source": 20, "target": 24, "value": 0.06733530997897653}, {"source": 20, "target": 25, "value": 0.009539418775736127}, {"source": 20, "target": 26, "value": 0.04799588594850676}, {"source": 20, "target": 27, "value": 0.021020352224135452}, {"source": 20, "target": 28, "value": 0.053743229973048603}, {"source": 20, "target": 29, "value": 0.19933955243189427}, {"source": 20, "target": 30, "value": 0.06305583411632042}, {"source": 20, "target": 31, "value": 0.2851274422143658}, {"source": 20, "target": 32, "value": 0.19155921895839365}, {"source": 20, "target": 33, "value": 0.08277073396923713}, {"source": 20, "target": 34, "value": 0.053687465427622046}, {"source": 20, "target": 35, "value": 0.09829838417907523}, {"source": 20, "target": 36, "value": 0.10853073659493824}, {"source": 20, "target": 37, "value": 0.12610580878052582}, {"source": 20, "target": 38, "value": 0.12308739688462475}, {"source": 20, "target": 39, "value": 0.060420921870559745}, {"source": 20, "target": 40, "value": 0.11266607325242792}, {"source": 20, "target": 41, "value": 0.02170061546027956}, {"source": 20, "target": 42, "value": 0.10493272100432692}, {"source": 20, "target": 43, "value": 0.08920369802665144}, {"source": 20, "target": 44, "value": 0.11863226485742813}, {"source": 20, "target": 45, "value": 0.04495165501870773}, {"source": 20, "target": 46, "value": 0.06912101078092017}, {"source": 20, "target": 47, "value": 0.12198820619296759}, {"source": 20, "target": 48, "value": 0.04685531950701103}, {"source": 20, "target": 49, "value": 0.052144129823728284}, {"source": 21, "target": 22, "value": 0.04973632212717157}, {"source": 21, "target": 23, "value": 0.04975842569429991}, {"source": 21, "target": 24, "value": 0.038782302792148976}, {"source": 21, "target": 25, "value": 0.011427172361082288}, {"source": 21, "target": 26, "value": 0.0336717408889102}, {"source": 21, "target": 27, "value": 0.017652089539499583}, {"source": 21, "target": 28, "value": 0.03769720484819847}, {"source": 21, "target": 29, "value": 0.07826460709519364}, {"source": 21, "target": 30, "value": 0.04242506786891703}, {"source": 21, "target": 31, "value": 0.0775376361474574}, {"source": 21, "target": 32, "value": 0.09235186682921949}, {"source": 21, "target": 33, "value": 0.024251747571617674}, {"source": 21, "target": 34, "value": 0.02695316974263187}, {"source": 21, "target": 35, "value": 0.11425430487274443}, {"source": 21, "target": 36, "value": 0.03361934217084581}, {"source": 21, "target": 37, "value": 0.04779836433653646}, {"source": 21, "target": 38, "value": 0.03615079461502089}, {"source": 21, "target": 39, "value": 0.038560802175264086}, {"source": 21, "target": 40, "value": 0.038614033840521096}, {"source": 21, "target": 41, "value": 0.016546279428954324}, {"source": 21, "target": 42, "value": 0.040351676915744705}, {"source": 21, "target": 43, "value": 0.058060189049224525}, {"source": 21, "target": 44, "value": 0.07990703179218109}, {"source": 21, "target": 45, "value": 0.03473529433219001}, {"source": 21, "target": 46, "value": 0.04721885350434312}, {"source": 21, "target": 47, "value": 0.05328817559776657}, {"source": 21, "target": 48, "value": 0.026621242125966522}, {"source": 21, "target": 49, "value": 0.03407200531241588}, {"source": 22, "target": 23, "value": 0.12899004228236816}, {"source": 22, "target": 24, "value": 0.16301874029473434}, {"source": 22, "target": 25, "value": 0.014665196579542458}, {"source": 22, "target": 26, "value": 0.06198602729378272}, {"source": 22, "target": 27, "value": 0.027604388828841486}, {"source": 22, "target": 28, "value": 0.07375295539280229}, {"source": 22, "target": 29, "value": 0.1754527473337704}, {"source": 22, "target": 30, "value": 0.09842403557942452}, {"source": 22, "target": 31, "value": 0.13140662927155744}, {"source": 22, "target": 32, "value": 0.15306109897501144}, {"source": 22, "target": 33, "value": 0.035184683441497444}, {"source": 22, "target": 34, "value": 0.045364265687097886}, {"source": 22, "target": 35, "value": 0.06007289148489125}, {"source": 22, "target": 36, "value": 0.05330371450873813}, {"source": 22, "target": 37, "value": 0.06439525617327001}, {"source": 22, "target": 38, "value": 0.034080785963656456}, {"source": 22, "target": 39, "value": 0.07712586718580927}, {"source": 22, "target": 40, "value": 0.059101885202871234}, {"source": 22, "target": 41, "value": 0.02533290857955105}, {"source": 22, "target": 42, "value": 0.06434595031599945}, {"source": 22, "target": 43, "value": 0.11287880240471014}, {"source": 22, "target": 44, "value": 0.08668392406841395}, {"source": 22, "target": 45, "value": 0.057115698751221244}, {"source": 22, "target": 46, "value": 0.08150941770471137}, {"source": 22, "target": 47, "value": 0.09425208832760508}, {"source": 22, "target": 48, "value": 0.06381170355690956}, {"source": 22, "target": 49, "value": 0.0715095115360773}, {"source": 23, "target": 24, "value": 0.16324855327182083}, {"source": 23, "target": 25, "value": 0.01512629803036149}, {"source": 23, "target": 26, "value": 0.06654831355698336}, {"source": 23, "target": 27, "value": 0.031458181485218686}, {"source": 23, "target": 28, "value": 0.08121266317790242}, {"source": 23, "target": 29, "value": 0.2221256151483807}, {"source": 23, "target": 30, "value": 0.11583477717011877}, {"source": 23, "target": 31, "value": 0.1728039289627893}, {"source": 23, "target": 32, "value": 0.18745359911866594}, {"source": 23, "target": 33, "value": 0.048325936019207955}, {"source": 23, "target": 34, "value": 0.05546729006882833}, {"source": 23, "target": 35, "value": 0.08216042706285517}, {"source": 23, "target": 36, "value": 0.07562157449302531}, {"source": 23, "target": 37, "value": 0.0767186926729545}, {"source": 23, "target": 38, "value": 0.04227234164516136}, {"source": 23, "target": 39, "value": 0.0979113670439627}, {"source": 23, "target": 40, "value": 0.07014952830594673}, {"source": 23, "target": 41, "value": 0.02605452899619243}, {"source": 23, "target": 42, "value": 0.07442140713154342}, {"source": 23, "target": 43, "value": 0.1422207806185257}, {"source": 23, "target": 44, "value": 0.10641486257830375}, {"source": 23, "target": 45, "value": 0.06588120988478839}, {"source": 23, "target": 46, "value": 0.09278608300242773}, {"source": 23, "target": 47, "value": 0.13040612982414346}, {"source": 23, "target": 48, "value": 0.06613293299381595}, {"source": 23, "target": 49, "value": 0.1255126437362401}, {"source": 24, "target": 25, "value": 0.03422418552681829}, {"source": 24, "target": 26, "value": 0.2152373236417454}, {"source": 24, "target": 27, "value": 0.05361593773050806}, {"source": 24, "target": 28, "value": 0.09221961101113636}, {"source": 24, "target": 29, "value": 0.1843916879902812}, {"source": 24, "target": 30, "value": 0.07217179519827625}, {"source": 24, "target": 31, "value": 0.15619986640556127}, {"source": 24, "target": 32, "value": 0.1306220544374413}, {"source": 24, "target": 33, "value": 0.04428175238415468}, {"source": 24, "target": 34, "value": 0.04040965077518963}, {"source": 24, "target": 35, "value": 0.05555586355146998}, {"source": 24, "target": 36, "value": 0.056063189970936914}, {"source": 24, "target": 37, "value": 0.05761479475576727}, {"source": 24, "target": 38, "value": 0.047650494819057386}, {"source": 24, "target": 39, "value": 0.05705702924740645}, {"source": 24, "target": 40, "value": 0.06406426678104889}, {"source": 24, "target": 41, "value": 0.03408651196826513}, {"source": 24, "target": 42, "value": 0.0813549326421852}, {"source": 24, "target": 43, "value": 0.21354822919577746}, {"source": 24, "target": 44, "value": 0.11517042954663322}, {"source": 24, "target": 45, "value": 0.058493256937243256}, {"source": 24, "target": 46, "value": 0.08779596506919982}, {"source": 24, "target": 47, "value": 0.11155911917001557}, {"source": 24, "target": 48, "value": 0.05867434689752386}, {"source": 24, "target": 49, "value": 0.12216285220788459}, {"source": 25, "target": 26, "value": 0.0391475129537315}, {"source": 25, "target": 27, "value": 0.9948063329644816}, {"source": 25, "target": 28, "value": 0.018200583318456667}, {"source": 25, "target": 29, "value": 0.020170722686911207}, {"source": 25, "target": 30, "value": 0.011261600827446238}, {"source": 25, "target": 31, "value": 0.018827340602423435}, {"source": 25, "target": 32, "value": 0.02208673355231542}, {"source": 25, "target": 33, "value": 0.006138366692347661}, {"source": 25, "target": 34, "value": 0.007174118950919032}, {"source": 25, "target": 35, "value": 0.011495484380832801}, {"source": 25, "target": 36, "value": 0.008783622842689732}, {"source": 25, "target": 37, "value": 0.00938661399391184}, {"source": 25, "target": 38, "value": 0.008374086424259738}, {"source": 25, "target": 39, "value": 0.009923459763519868}, {"source": 25, "target": 40, "value": 0.009794818420110539}, {"source": 25, "target": 41, "value": 0.02198430907660212}, {"source": 25, "target": 42, "value": 0.032841303285841374}, {"source": 25, "target": 43, "value": 0.019508774161448583}, {"source": 25, "target": 44, "value": 0.01567688731475479}, {"source": 25, "target": 45, "value": 0.012576490633058216}, {"source": 25, "target": 46, "value": 0.02220228937671465}, {"source": 25, "target": 47, "value": 0.01581863295595152}, {"source": 25, "target": 48, "value": 0.01019511171517653}, {"source": 25, "target": 49, "value": 0.02508544355178439}, {"source": 26, "target": 27, "value": 0.06971354616831603}, {"source": 26, "target": 28, "value": 0.28896371266065957}, {"source": 26, "target": 29, "value": 0.09777298057360245}, {"source": 26, "target": 30, "value": 0.07293433475732876}, {"source": 26, "target": 31, "value": 0.09168859863541486}, {"source": 26, "target": 32, "value": 0.14950368842235764}, {"source": 26, "target": 33, "value": 0.026527466940121838}, {"source": 26, "target": 34, "value": 0.030960926345726683}, {"source": 26, "target": 35, "value": 0.07340145038558862}, {"source": 26, "target": 36, "value": 0.04050070225094808}, {"source": 26, "target": 37, "value": 0.047549090126172006}, {"source": 26, "target": 38, "value": 0.02613536741744316}, {"source": 26, "target": 39, "value": 0.05045889111062155}, {"source": 26, "target": 40, "value": 0.04318559952251411}, {"source": 26, "target": 41, "value": 0.01915421419313464}, {"source": 26, "target": 42, "value": 0.04801395871417954}, {"source": 26, "target": 43, "value": 0.09425835554009143}, {"source": 26, "target": 44, "value": 0.06334250758365656}, {"source": 26, "target": 45, "value": 0.043225926896271305}, {"source": 26, "target": 46, "value": 0.10197063967414428}, {"source": 26, "target": 47, "value": 0.08149200086312805}, {"source": 26, "target": 48, "value": 0.03522626381129111}, {"source": 26, "target": 49, "value": 0.048642187820134054}, {"source": 27, "target": 28, "value": 0.03356160310896201}, {"source": 27, "target": 29, "value": 0.048915933624748276}, {"source": 27, "target": 30, "value": 0.021936022812879156}, {"source": 27, "target": 31, "value": 0.04472926518246618}, {"source": 27, "target": 32, "value": 0.05860712956519575}, {"source": 27, "target": 33, "value": 0.020921010441315436}, {"source": 27, "target": 34, "value": 0.07747940022956984}, {"source": 27, "target": 35, "value": 0.025540601594337346}, {"source": 27, "target": 36, "value": 0.0710059423729146}, {"source": 27, "target": 37, "value": 0.01983167590276391}, {"source": 27, "target": 38, "value": 0.020341857476740572}, {"source": 27, "target": 39, "value": 0.047797125097521466}, {"source": 27, "target": 40, "value": 0.02264719748316254}, {"source": 27, "target": 41, "value": 0.03432278074189211}, {"source": 27, "target": 42, "value": 0.04202757628173809}, {"source": 27, "target": 43, "value": 0.04645908985943502}, {"source": 27, "target": 44, "value": 0.03477871142970312}, {"source": 27, "target": 45, "value": 0.027389721902591653}, {"source": 27, "target": 46, "value": 0.043273756856926804}, {"source": 27, "target": 47, "value": 0.04856112267638501}, {"source": 27, "target": 48, "value": 0.02469610857295471}, {"source": 27, "target": 49, "value": 0.08164103806003971}, {"source": 28, "target": 29, "value": 0.12789570726427513}, {"source": 28, "target": 30, "value": 0.07491854988178451}, {"source": 28, "target": 31, "value": 0.10459577398881605}, {"source": 28, "target": 32, "value": 0.1319562018247859}, {"source": 28, "target": 33, "value": 0.03150580187789826}, {"source": 28, "target": 34, "value": 0.03572939067522623}, {"source": 28, "target": 35, "value": 0.05864595775824166}, {"source": 28, "target": 36, "value": 0.043180066506513064}, {"source": 28, "target": 37, "value": 0.053288950777042085}, {"source": 28, "target": 38, "value": 0.027783202618276857}, {"source": 28, "target": 39, "value": 0.06136908998417628}, {"source": 28, "target": 40, "value": 0.0480380915225168}, {"source": 28, "target": 41, "value": 0.020706647526748095}, {"source": 28, "target": 42, "value": 0.05381146944634478}, {"source": 28, "target": 43, "value": 0.09095933951530116}, {"source": 28, "target": 44, "value": 0.07117842897837318}, {"source": 28, "target": 45, "value": 0.04764026843451958}, {"source": 28, "target": 46, "value": 0.07518385268251268}, {"source": 28, "target": 47, "value": 0.08324121643819753}, {"source": 28, "target": 48, "value": 0.04235659240664808}, {"source": 28, "target": 49, "value": 0.07042843134577174}, {"source": 29, "target": 30, "value": 0.3768806508401714}, {"source": 29, "target": 31, "value": 0.3223623983236505}, {"source": 29, "target": 32, "value": 0.397847089305923}, {"source": 29, "target": 33, "value": 0.08941188163278076}, {"source": 29, "target": 34, "value": 0.09435279504914755}, {"source": 29, "target": 35, "value": 0.12885031141149642}, {"source": 29, "target": 36, "value": 0.1262613943086115}, {"source": 29, "target": 37, "value": 0.15563604350806443}, {"source": 29, "target": 38, "value": 0.08783456904849776}, {"source": 29, "target": 39, "value": 0.1817940779937384}, {"source": 29, "target": 40, "value": 0.11910254828835964}, {"source": 29, "target": 41, "value": 0.038127565211682805}, {"source": 29, "target": 42, "value": 0.12258890434956501}, {"source": 29, "target": 43, "value": 0.210849054182575}, {"source": 29, "target": 44, "value": 0.15091736000113776}, {"source": 29, "target": 45, "value": 0.09030165504756696}, {"source": 29, "target": 46, "value": 0.1301113766989676}, {"source": 29, "target": 47, "value": 0.27384502010740036}, {"source": 29, "target": 48, "value": 0.13445607163915282}, {"source": 29, "target": 49, "value": 0.2901078283948487}, {"source": 30, "target": 31, "value": 0.16953149495336886}, {"source": 30, "target": 32, "value": 0.5405941537021428}, {"source": 30, "target": 33, "value": 0.03223227167002705}, {"source": 30, "target": 34, "value": 0.0772274146984747}, {"source": 30, "target": 35, "value": 0.15006643912091336}, {"source": 30, "target": 36, "value": 0.06290632108930694}, {"source": 30, "target": 37, "value": 0.08433545834712745}, {"source": 30, "target": 38, "value": 0.0312084669053741}, {"source": 30, "target": 39, "value": 0.19634254823605804}, {"source": 30, "target": 40, "value": 0.0583959812863693}, {"source": 30, "target": 41, "value": 0.02100752909765232}, {"source": 30, "target": 42, "value": 0.05763808244695363}, {"source": 30, "target": 43, "value": 0.0986126689091454}, {"source": 30, "target": 44, "value": 0.07695555060625442}, {"source": 30, "target": 45, "value": 0.04783989362757858}, {"source": 30, "target": 46, "value": 0.06990862829689577}, {"source": 30, "target": 47, "value": 0.08792172662920916}, {"source": 30, "target": 48, "value": 0.04589979859312172}, {"source": 30, "target": 49, "value": 0.05374502058351027}, {"source": 31, "target": 32, "value": 0.49564188592337477}, {"source": 31, "target": 33, "value": 0.1585193499335637}, {"source": 31, "target": 34, "value": 0.10825867732165069}, {"source": 31, "target": 35, "value": 0.2618388629547055}, {"source": 31, "target": 36, "value": 0.2900418255388877}, {"source": 31, "target": 37, "value": 0.26893510946379195}, {"source": 31, "target": 38, "value": 0.22458144417846998}, {"source": 31, "target": 39, "value": 0.18254890208220453}, {"source": 31, "target": 40, "value": 0.2603378788514959}, {"source": 31, "target": 41, "value": 0.0388108703534153}, {"source": 31, "target": 42, "value": 0.2360590335342727}, {"source": 31, "target": 43, "value": 0.19263799111539823}, {"source": 31, "target": 44, "value": 0.16193271656779037}, {"source": 31, "target": 45, "value": 0.10165401268788919}, {"source": 31, "target": 46, "value": 0.16154961929702066}, {"source": 31, "target": 47, "value": 0.24658412118998393}, {"source": 31, "target": 48, "value": 0.11904628930832017}, {"source": 31, "target": 49, "value": 0.18329580900934558}, {"source": 32, "target": 33, "value": 0.15975439797113195}, {"source": 32, "target": 34, "value": 0.3236027725624956}, {"source": 32, "target": 35, "value": 0.48131113321437297}, {"source": 32, "target": 36, "value": 0.4010096581623547}, {"source": 32, "target": 37, "value": 0.5553843637196457}, {"source": 32, "target": 38, "value": 0.17949724886185411}, {"source": 32, "target": 39, "value": 0.5574546398199356}, {"source": 32, "target": 40, "value": 0.4731563056202223}, {"source": 32, "target": 41, "value": 0.054899588400711956}, {"source": 32, "target": 42, "value": 0.16037436824148485}, {"source": 32, "target": 43, "value": 0.20847130180351398}, {"source": 32, "target": 44, "value": 0.16797290670477433}, {"source": 32, "target": 45, "value": 0.10404683767067027}, {"source": 32, "target": 46, "value": 0.1506697104355552}, {"source": 32, "target": 47, "value": 0.2115990512588953}, {"source": 32, "target": 48, "value": 0.10363604658518481}, {"source": 32, "target": 49, "value": 0.12146602087232788}, {"source": 33, "target": 34, "value": 0.2381335351929099}, {"source": 33, "target": 35, "value": 0.11948789168436932}, {"source": 33, "target": 36, "value": 0.16115110504771382}, {"source": 33, "target": 37, "value": 0.07684171579014497}, {"source": 33, "target": 38, "value": 0.9786903178125448}, {"source": 33, "target": 39, "value": 0.07095752748776582}, {"source": 33, "target": 40, "value": 0.1143984081356705}, {"source": 33, "target": 41, "value": 0.012864733680898967}, {"source": 33, "target": 42, "value": 0.07620384871708819}, {"source": 33, "target": 43, "value": 0.072217283561496}, {"source": 33, "target": 44, "value": 0.05174004669035093}, {"source": 33, "target": 45, "value": 0.04041801066865298}, {"source": 33, "target": 46, "value": 0.046456955013102555}, {"source": 33, "target": 47, "value": 0.1063815914652912}, {"source": 33, "target": 48, "value": 0.04064311705125061}, {"source": 33, "target": 49, "value": 0.09395099136869256}, {"source": 34, "target": 35, "value": 0.12013920315234178}, {"source": 34, "target": 36, "value": 0.8262830453340713}, {"source": 34, "target": 37, "value": 0.06322595459464488}, {"source": 34, "target": 38, "value": 0.24233350177447632}, {"source": 34, "target": 39, "value": 0.5001943740818366}, {"source": 34, "target": 40, "value": 0.06530446056761527}, {"source": 34, "target": 41, "value": 0.016923848000818354}, {"source": 34, "target": 42, "value": 0.04874319981573271}, {"source": 34, "target": 43, "value": 0.062275712526559765}, {"source": 34, "target": 44, "value": 0.048617524464359525}, {"source": 34, "target": 45, "value": 0.03918925382176507}, {"source": 34, "target": 46, "value": 0.04886863936859561}, {"source": 34, "target": 47, "value": 0.060230679399228555}, {"source": 34, "target": 48, "value": 0.028524676537891255}, {"source": 34, "target": 49, "value": 0.03416128619457744}, {"source": 35, "target": 36, "value": 0.3202352307591333}, {"source": 35, "target": 37, "value": 0.14221186227638555}, {"source": 35, "target": 38, "value": 0.11229782562430059}, {"source": 35, "target": 39, "value": 0.11783369440096435}, {"source": 35, "target": 40, "value": 0.13731845470292983}, {"source": 35, "target": 41, "value": 0.03388143788257491}, {"source": 35, "target": 42, "value": 0.09150630629337024}, {"source": 35, "target": 43, "value": 0.08210324870219413}, {"source": 35, "target": 44, "value": 0.08345563378772133}, {"source": 35, "target": 45, "value": 0.045049612286354665}, {"source": 35, "target": 46, "value": 0.06723316976772067}, {"source": 35, "target": 47, "value": 0.09903261812537645}, {"source": 35, "target": 48, "value": 0.06291635547563715}, {"source": 35, "target": 49, "value": 0.0445580644100148}, {"source": 36, "target": 37, "value": 0.14341914256782395}, {"source": 36, "target": 38, "value": 0.15141959113256104}, {"source": 36, "target": 39, "value": 0.4268405919005104}, {"source": 36, "target": 40, "value": 0.1696393985079011}, {"source": 36, "target": 41, "value": 0.018617896303705094}, {"source": 36, "target": 42, "value": 0.09087825669466672}, {"source": 36, "target": 43, "value": 0.08074196253995668}, {"source": 36, "target": 44, "value": 0.08693199004389186}, {"source": 36, "target": 45, "value": 0.04243335296269134}, {"source": 36, "target": 46, "value": 0.060740668677231255}, {"source": 36, "target": 47, "value": 0.10825720741517007}, {"source": 36, "target": 48, "value": 0.1984209452768193}, {"source": 36, "target": 49, "value": 0.04623285761864197}, {"source": 37, "target": 38, "value": 0.09945189557622186}, {"source": 37, "target": 39, "value": 0.10425126525885332}, {"source": 37, "target": 40, "value": 0.11254930488633577}, {"source": 37, "target": 41, "value": 0.022175402409082046}, {"source": 37, "target": 42, "value": 0.09101277827971008}, {"source": 37, "target": 43, "value": 0.08332733185863704}, {"source": 37, "target": 44, "value": 0.07465174101917842}, {"source": 37, "target": 45, "value": 0.04607766714079194}, {"source": 37, "target": 46, "value": 0.06713743137862363}, {"source": 37, "target": 47, "value": 0.10656103069401271}, {"source": 37, "target": 48, "value": 0.04843574667555119}, {"source": 37, "target": 49, "value": 0.04367559220186229}, {"source": 38, "target": 39, "value": 0.07059772276119433}, {"source": 38, "target": 40, "value": 0.1415274341967874}, {"source": 38, "target": 41, "value": 0.01579550774374318}, {"source": 38, "target": 42, "value": 0.10149216572516523}, {"source": 38, "target": 43, "value": 0.05652353759788166}, {"source": 38, "target": 44, "value": 0.048544678615212486}, {"source": 38, "target": 45, "value": 0.033266470276060535}, {"source": 38, "target": 46, "value": 0.048482185429644525}, {"source": 38, "target": 47, "value": 0.08697599833299198}, {"source": 38, "target": 48, "value": 0.03284022259982543}, {"source": 38, "target": 49, "value": 0.03249995574926931}, {"source": 39, "target": 40, "value": 0.07380760866659722}, {"source": 39, "target": 41, "value": 0.021974126515104633}, {"source": 39, "target": 42, "value": 0.059044744365881995}, {"source": 39, "target": 43, "value": 0.09166087258875506}, {"source": 39, "target": 44, "value": 0.07562449330590021}, {"source": 39, "target": 45, "value": 0.053270609092595914}, {"source": 39, "target": 46, "value": 0.07123347528836704}, {"source": 39, "target": 47, "value": 0.0927541951643271}, {"source": 39, "target": 48, "value": 0.04696087803446643}, {"source": 39, "target": 49, "value": 0.054741887461495935}, {"source": 40, "target": 41, "value": 0.020861410687029736}, {"source": 40, "target": 42, "value": 0.09817900401132647}, {"source": 40, "target": 43, "value": 0.08604697039646433}, {"source": 40, "target": 44, "value": 0.09104306087452473}, {"source": 40, "target": 45, "value": 0.04909699216522276}, {"source": 40, "target": 46, "value": 0.06942512359954886}, {"source": 40, "target": 47, "value": 0.10677410432884117}, {"source": 40, "target": 48, "value": 0.052143987528546536}, {"source": 40, "target": 49, "value": 0.05621471148131708}, {"source": 41, "target": 42, "value": 0.3710168869604183}, {"source": 41, "target": 43, "value": 0.03345004770186661}, {"source": 41, "target": 44, "value": 0.08440812561768453}, {"source": 41, "target": 45, "value": 0.07602302415361298}, {"source": 41, "target": 46, "value": 0.26418961032052074}, {"source": 41, "target": 47, "value": 0.028473484015870767}, {"source": 41, "target": 48, "value": 0.014948868370789065}, {"source": 41, "target": 49, "value": 0.023845220882120956}, {"source": 42, "target": 43, "value": 0.09833804586737467}, {"source": 42, "target": 44, "value": 0.08408675863183875}, {"source": 42, "target": 45, "value": 0.057862855870740214}, {"source": 42, "target": 46, "value": 0.2648515448641455}, {"source": 42, "target": 47, "value": 0.10193454473210878}, {"source": 42, "target": 48, "value": 0.04717542222759561}, {"source": 42, "target": 49, "value": 0.06758417160826315}, {"source": 43, "target": 44, "value": 0.14461647869405142}, {"source": 43, "target": 45, "value": 0.11282469864830766}, {"source": 43, "target": 46, "value": 0.1355759409082575}, {"source": 43, "target": 47, "value": 0.1978806788959369}, {"source": 43, "target": 48, "value": 0.10748297293189266}, {"source": 43, "target": 49, "value": 0.222185058288652}, {"source": 44, "target": 45, "value": 0.8823791290124297}, {"source": 44, "target": 46, "value": 0.8718611222685416}, {"source": 44, "target": 47, "value": 0.12789905538724747}, {"source": 44, "target": 48, "value": 0.0814339582872714}, {"source": 44, "target": 49, "value": 0.122783558867891}, {"source": 45, "target": 46, "value": 0.9073231163490729}, {"source": 45, "target": 47, "value": 0.08319971935624043}, {"source": 45, "target": 48, "value": 0.03900835596769652}, {"source": 45, "target": 49, "value": 0.06301392167177408}, {"source": 46, "target": 47, "value": 0.10483392492866309}, {"source": 46, "target": 48, "value": 0.05196040931998269}, {"source": 46, "target": 49, "value": 0.07653439826772558}, {"source": 47, "target": 48, "value": 0.12462257895862446}, {"source": 47, "target": 49, "value": 0.42572517990769065}, {"source": 48, "target": 49, "value": 0.16094893782061687}]}